setup.py
DistRv01/Binomialdistribution.py
DistRv01/Gaussiandistribution.py
DistRv01/Generaldistribution.py
DistRv01/__init__.py
DistRv01.egg-info/PKG-INFO
DistRv01.egg-info/SOURCES.txt
DistRv01.egg-info/dependency_links.txt
DistRv01.egg-info/not-zip-safe
DistRv01.egg-info/top_level.txt